streamsplit/__init__.py
streamsplit/__main__.py
streamsplit/streamsplit.py
streamsplit-0.1.1.dist-info/METADATA
streamsplit-0.1.1.dist-info/RECORD
streamsplit-0.1.1.dist-info/WHEEL
streamsplit-0.1.1.dist-info/top_level.txt
