Metadata-Version: 2.1
Name: streamsplit
Version: 0.1.1
Summary: A utility to extract TCP streams from (large) pcap files
Home-page: https://github.com/schalowj/streamsplit
Author: J.A. Schalow
Author-email: schalowj@gmail.com
License: UNKNOWN
Platform: UNKNOWN
Classifier: Programming Language :: Python :: 2.7
Classifier: License :: OSI Approved :: GNU General Public License v3 or later (GPLv3+)
Classifier: Operating System :: OS Independent
